MANIFEST.in
README.md
setup.py
bounding_box/Ubuntu-B.ttf
bounding_box/__init__.py
bounding_box/bounding_box.py
bounding_box.egg-info/PKG-INFO
bounding_box.egg-info/SOURCES.txt
bounding_box.egg-info/dependency_links.txt
bounding_box.egg-info/requires.txt
bounding_box.egg-info/top_level.txt