Metadata-Version: 1.2
Name: bounding_box
Version: 0.1.3
Summary: A tool to plot pretty bounding boxes around objects.
Home-page: https://github.com/nalepae/bounding_box
Author: Manu NALEPA
Author-email: nalepae@gmail.com
License: BSD
Platform: UNKNOWN
Requires-Python: >=2.7
